hojo/__init__.py
hojo/base.py
hojo/config.py
hojo/connection.py
hojo/converter.py
hojo/errors.py
hojo/orm/manager.py
hojo/orm/mapper.py
hojo/orm/queryset.py
hojo/schema.py
hojo-0.3.1.dist-info/LICENSE
hojo-0.3.1.dist-info/METADATA
hojo-0.3.1.dist-info/WHEEL
hojo-0.3.1.dist-info/RECORD
