Metadata-Version: 2.1
Name: hojo
Version: 0.3.1
Summary: Hojo: An ORM built on top of SQL Alchemy
License: MIT
Author: Rafael Izidoro
Author-email: izidoro.me@gmail.com
Requires-Python: >=3.11,<4.0
Classifier: License :: OSI Approved :: MIT License
Classifier: Programming Language :: Python :: 3
Classifier: Programming Language :: Python :: 3.11
Requires-Dist: SQLAlchemy (>=2.0.23,<3.0.0)
Requires-Dist: alembic (>=1.13.0,<2.0.0)
Requires-Dist: attrs (>=23.1.0,<24.0.0)
Requires-Dist: cattrs (>=23.2.3,<24.0.0)
Requires-Dist: pendulum (>=3.0.0,<4.0.0)
Requires-Dist: pg8000 (>=1.30.3,<2.0.0)
Requires-Dist: pluralizer (>=1.2.0,<2.0.0)
Requires-Dist: sqlalchemy-utils (>=0.41.1,<0.42.0)
Requires-Dist: stringcase (>=1.2.0,<2.0.0)
Requires-Dist: uuid6 (>=2023.5.2,<2024.0.0)
